sqlguardian/__init__.py
sqlguardian/py.typed
sqlguardian-0.3.1.dist-info/METADATA
sqlguardian-0.3.1.dist-info/WHEEL
sqlguardian-0.3.1.dist-info/licenses/LICENSE
sqlguardian-0.3.1.dist-info/RECORD
