Metadata-Version: 2.4
Name: sqlguardian
Version: 0.3.1
Summary: SQLGuardian.
Project-URL: homepage, https://github.com/MicaelJarniac/sqlguardian
Project-URL: source, https://github.com/MicaelJarniac/sqlguardian
Project-URL: download, https://pypi.org/project/sqlguardian/#files
Project-URL: changelog, https://github.com/MicaelJarniac/sqlguardian/blob/main/docs/CHANGELOG.md
Project-URL: documentation, https://sqlguardian.readthedocs.io
Project-URL: issues, https://github.com/MicaelJarniac/sqlguardian/issues
Author-email: Micael Jarniac <micael@jarniac.dev>
License: MIT
License-File: LICENSE
Classifier: Development Status :: 1 - Planning
Classifier: License :: OSI Approved :: MIT License
Classifier: Natural Language :: English
Classifier: Operating System :: OS Independent
Classifier: Programming Language :: Python :: 3
Classifier: Typing :: Typed
Requires-Python: >=3.13
Requires-Dist: loguru>=0.7.3
Requires-Dist: pydantic>=2.11.9
Requires-Dist: pyyaml>=6.0.2
Requires-Dist: sqlglot[rs]>=27.15.3
